sopel_modules.imdb-1.2.2.post1-py3.9-nspkg.pth
sopel_modules/imdb/__init__.py
sopel_modules/imdb/imdb.py
sopel_modules.imdb-1.2.2.post1.dist-info/LICENSE
sopel_modules.imdb-1.2.2.post1.dist-info/METADATA
sopel_modules.imdb-1.2.2.post1.dist-info/WHEEL
sopel_modules.imdb-1.2.2.post1.dist-info/namespace_packages.txt
sopel_modules.imdb-1.2.2.post1.dist-info/top_level.txt
sopel_modules.imdb-1.2.2.post1.dist-info/RECORD
