Metadata-Version: 2.1
Name: sopel-modules.imdb
Version: 1.2.2.post1
Summary: Re-implementation of the imdb module for Sopel (replaced)
Home-page: http://github.com/rustybower/sopel-imdb
Author: Rusty Bower
Author-email: rusty@rustybower.com
License: MIT License
Platform: UNKNOWN
License-File: LICENSE
Requires-Dist: requests
Requires-Dist: sopel<8,>=7
